pyinuse/__init__.py
pyinuse/pyinuse.py
pyinuse-0.1.2.dist-info/AUTHORS.md
pyinuse-0.1.2.dist-info/LICENSE
pyinuse-0.1.2.dist-info/METADATA
pyinuse-0.1.2.dist-info/WHEEL
pyinuse-0.1.2.dist-info/top_level.txt
pyinuse-0.1.2.dist-info/RECORD
