Metadata-Version: 2.1
Name: pyinuse
Version: 0.1.2
Summary: Official client for InUse
Home-page: https://github.com/optimdata/pyinuse
Author: Othman Moumni Abdou
Author-email: othman.moumniabdou@inuse.eu
License: MIT license
Keywords: inuse,client,api
Platform: UNKNOWN
Classifier: Development Status :: 2 - Pre-Alpha
Classifier: Intended Audience :: Developers
Classifier: License :: OSI Approved :: MIT License
Classifier: Natural Language :: English
Classifier: Programming Language :: Python :: 3
Classifier: Programming Language :: Python :: 3.6
Classifier: Programming Language :: Python :: 3.7
Classifier: Programming Language :: Python :: 3.8
Requires-Dist: requests
